{
  "posts": [
    {
      "id": 1,
      "text": "jugar alguna mondá",
      "state": "done"
    },
    {
      "id": 2,
      "text": "Otra cosa",
      "state": "done"
    },
    {
      "id": 3,
      "text": "Otro ejemplo",
      "state": "done"
    },
    {
      "id": 4,
      "text": "Otro ejemplo",
      "state": "done"
    },
    {
      "id": 5,
      "text": "Otro ejemplo",
      "state": "done"
    },
    {
      "id": 6,
      "text": "Otro ejemplo",
      "state": "done"
    },
    {
      "id": 7,
      "text": "Tal vez uno más",
      "state": "pending"
    }
  ]
}